unitreport/__init__.py
unitreport/__main__.py
unitreport/decorators.py
unitreport/generate.py
unitreport/templates/index.html
unitreport/templates/main.css
unitreport-0.1.1.dist-info/LICENSE
unitreport-0.1.1.dist-info/METADATA
unitreport-0.1.1.dist-info/WHEEL
unitreport-0.1.1.dist-info/top_level.txt
unitreport-0.1.1.dist-info/RECORD
