Metadata-Version: 2.1
Name: unitreport
Version: 0.1.1
Summary: A small unittest-based tool for generating single page html reports in Python.
Home-page: https://github.com/annahadji/unitreport
Author: annahadji
Author-email: annahadji@users.noreply.github.com
License: UNKNOWN
Keywords: static unittest report generator Markdown plots tables
Platform: UNKNOWN
Classifier: Development Status :: 4 - Beta
Classifier: License :: OSI Approved :: MIT License
Classifier: Natural Language :: English
Classifier: Operating System :: OS Independent
Classifier: Programming Language :: Python :: 3 :: Only
Classifier: Topic :: Scientific/Engineering :: Visualization
Requires-Python: >=3.6
Requires-Dist: jinja2
Requires-Dist: markdown
Requires-Dist: matplotlib
